sbuilder/__init__.py
sbuilder/sbuilder.py
sbuilder-1.1a0.dist-info/METADATA
sbuilder-1.1a0.dist-info/WHEEL
sbuilder-1.1a0.dist-info/top_level.txt
sbuilder-1.1a0.dist-info/RECORD
