Metadata-Version: 2.4
Name: sbuilder
Version: 1.1a0
Summary: A simple Python library to build and run tasks.
Author: zboxjpg
License: MIT
Requires-Python: >=3.10
